[{"__type__":"cc.SpriteFrame","content":{"name":"lb_ysc_BG00_1","texture":"f3N4b5XHNFYZZpQFHZ1gpd","rect":[0,0,1131,639],"offset":[0,0],"originalSize":[1131,639]}},{"__type__":"cc.SpriteFrame","content":{"name":"lb_ysc_man_01_1","texture":"d0iQNagj1GmLb2D2PS3KlW","rect":[0,0,73,61],"offset":[0,0],"originalSize":[73,61]}},[{"__type__":"cc.Prefab","_name":"lb_ysc_level17","data":{"__id__":1},"asyncLoadAssets":null},{"__type__":"cc.Node","_name":"lb_level17","_children":[{"__id__":2},{"__id__":3},{"__id__":5},{"__id__":7},{"__type__":"cc.Node","_name":"tip","_parent":{"__id__":1},"_prefab":{"__type__":"cc.PrefabInfo","root":{"__id__":1},"asset":{"__uuid__":"73M62JjrhDPrsa2yE8QD8X"},"fileId":"37XlzVuRlBmblLZ/ZEruN5"},"_position":{"__type__":"cc.Vec2","y":-219}},{"__id__":8},{"__id__":9},{"__id__":10},{"__id__":11},{"__id__":12}],"_components":[{"__type__":"cc.Widget","node":{"__id__":1},"_alignFlags":45,"_left":0.08000000000000002,"_right":0.07999999999999996,"_top":0.07999999999999996,"_bottom":0.08000000000000002,"_isAbsLeft":false,"_isAbsRight":false,"_isAbsTop":false,"_isAbsBottom":false}],"_prefab":{"__type__":"cc.PrefabInfo","root":{"__id__":1},"asset":{"__uuid__":"73M62JjrhDPrsa2yE8QD8X"},"fileId":"8e5NrhZq1POaLoCo4nn3c8"},"_contentSize":{"__type__":"cc.Size","width":1120.56,"height":630}},{"__type__":"cc.Node","_name":"BG00","_parent":{"__id__":1},"_components":[{"__type__":"cc.Sprite","node":{"__id__":2},"_spriteFrame":{"__uuid__":"0aTYgW/uhPdriIoT5Wr0m0"},"_sizeMode":0},{"__type__":"cc.Widget","node":{"__id__":2},"_alignFlags":45,"_left":-0.22000000000002728,"_right":-0.22000000000002728,"_originalWidth":960,"_originalHeight":540}],"_prefab":{"__type__":"cc.PrefabInfo","root":{"__id__":1},"asset":{"__uuid__":"73M62JjrhDPrsa2yE8QD8X"},"fileId":"cdOUTj6iRBT5mKYpPjc9lg"},"_contentSize":{"__type__":"cc.Size","width":1121,"height":630}},{"__type__":"cc.Node","_name":"boy","_parent":{"__id__":1},"_children":[{"__id__":4}],"_components":[{"__type__":"cc.Sprite","node":{"__id__":3},"_spriteFrame":{"__uuid__":"1bEK9fghJAQ4zW61UHv30X"},"_sizeMode":0},{"__type__":"cc.RigidBody","node":{"__id__":3},"_type":0,"enabledContactListener":true},{"__type__":"cc.PhysicsCircleCollider","node":{"__id__":3},"_radius":33},{"__type__":"5883b0adEtEV7mOEZ29DVJI","node":{"__id__":3}},{"__type__":"cc.CircleCollider","node":{"__id__":3},"_radius":33}],"_prefab":{"__type__":"cc.PrefabInfo","root":{"__id__":1},"asset":{"__uuid__":"73M62JjrhDPrsa2yE8QD8X"},"fileId":"242mZgGzdLb7f/PZvhT//o"},"_contentSize":{"__type__":"cc.Size","width":73,"height":61},"_position":{"__type__":"cc.Vec2","x":-84,"y":229},"groupIndex":1},{"__type__":"cc.Node","_name":"startParticle","_parent":{"__id__":3},"_components":[{"__type__":"cc.ParticleSystem","node":{"__id__":4},"_custom":true,"_file":{"__uuid__":"b2aHrECZ5APKGS/0d2hvT1"},"_texture":{"__uuid__":"e12EPN2/FAap5K1ZEuQk8F"},"_autoRemoveOnFinish":true,"_duration":1,"_emissionRate":3,"_startColor":{"__type__":"cc.Color","r":218,"g":33,"b":33},"_gravity":{"__type__":"cc.Vec2","x":0.25,"y":0.8600000143051147}}],"_prefab":{"__type__":"cc.PrefabInfo","root":{"__id__":1},"asset":{"__uuid__":"73M62JjrhDPrsa2yE8QD8X"},"fileId":"c39t2t/jdKgK3VzYwuLkFO"},"_position":{"__type__":"cc.Vec2","y":20}},{"__type__":"cc.Node","_name":"gril","_parent":{"__id__":1},"_children":[{"__id__":6}],"_components":[{"__type__":"cc.Sprite","node":{"__id__":5},"_spriteFrame":{"__uuid__":"93ihb/8/VH2rPguiqezlOi"},"_sizeMode":0},{"__type__":"cc.RigidBody","node":{"__id__":5},"_type":0,"enabledContactListener":true},{"__type__":"cc.PhysicsCircleCollider","node":{"__id__":5},"_radius":33},{"__type__":"cc.CircleCollider","node":{"__id__":5},"_radius":33}],"_prefab":{"__type__":"cc.PrefabInfo","root":{"__id__":1},"asset":{"__uuid__":"73M62JjrhDPrsa2yE8QD8X"},"fileId":"45y6l1saBA7YRGUi5WvaTh"},"_contentSize":{"__type__":"cc.Size","width":73,"height":61},"_position":{"__type__":"cc.Vec2","x":71,"y":229},"groupIndex":1},{"__type__":"cc.Node","_name":"startParticle","_parent":{"__id__":5},"_components":[{"__type__":"cc.ParticleSystem","node":{"__id__":6},"_custom":true,"_file":{"__uuid__":"b2aHrECZ5APKGS/0d2hvT1"},"_texture":{"__uuid__":"e12EPN2/FAap5K1ZEuQk8F"},"_autoRemoveOnFinish":true,"_duration":1,"_emissionRate":3,"_startColor":{"__type__":"cc.Color","r":218,"g":33,"b":33},"_gravity":{"__type__":"cc.Vec2","x":0.25,"y":0.8600000143051147}}],"_prefab":{"__type__":"cc.PrefabInfo","root":{"__id__":1},"asset":{"__uuid__":"73M62JjrhDPrsa2yE8QD8X"},"fileId":"c39t2t/jdKgK3VzYwuLkFO"},"_position":{"__type__":"cc.Vec2","y":20}},{"__type__":"cc.Node","_name":"Splash","_parent":{"__id__":1},"_components":[{"__type__":"cc.Sprite","node":{"__id__":7},"_spriteFrame":{"__uuid__":"a2MjXRFdtLlYQ5ouAFv/+R"},"_sizeMode":0},{"__type__":"cc.Widget","node":{"__id__":7},"_alignFlags":20,"_right":567,"_top":275,"_originalWidth":100},{"__type__":"cc.RigidBody","node":{"__id__":7},"_type":0},{"__type__":"cc.BoxCollider","node":{"__id__":7},"_size":{"__type__":"cc.Size","width":600,"height":70}},{"__type__":"cc.PhysicsBoxCollider","node":{"__id__":7},"_size":{"__type__":"cc.Size","width":600,"height":70}}],"_prefab":{"__type__":"cc.PrefabInfo","root":{"__id__":1},"asset":{"__uuid__":"73M62JjrhDPrsa2yE8QD8X"},"fileId":"54+S2oJmRPm6scBlauoCmj"},"_color":{"__type__":"cc.Color","r":107,"g":134,"b":197},"_contentSize":{"__type__":"cc.Size","width":600,"height":70},"_position":{"__type__":"cc.Vec2","y":-280},"groupIndex":1},{"__type__":"cc.Node","_name":"Splash2","_parent":{"__id__":1},"_components":[{"__type__":"cc.Sprite","node":{"__id__":8},"_spriteFrame":{"__uuid__":"a2MjXRFdtLlYQ5ouAFv/+R"},"_sizeMode":0},{"__type__":"cc.Widget","node":{"__id__":8},"_alignFlags":17,"_right":567,"_top":55,"_bottom":-50,"_originalWidth":100,"_originalHeight":150},{"__type__":"cc.RigidBody","node":{"__id__":8},"_type":0},{"__type__":"cc.BoxCollider","node":{"__id__":8},"_size":{"__type__":"cc.Size","width":45,"height":200}},{"__type__":"cc.PhysicsBoxCollider","node":{"__id__":8},"_size":{"__type__":"cc.Size","width":45,"height":200}}],"_prefab":{"__type__":"cc.PrefabInfo","root":{"__id__":1},"asset":{"__uuid__":"73M62JjrhDPrsa2yE8QD8X"},"fileId":"8eDGvkehBF96F83kuGoJP5"},"_color":{"__type__":"cc.Color","r":107,"g":134,"b":197},"_contentSize":{"__type__":"cc.Size","width":45,"height":200},"_position":{"__type__":"cc.Vec2","y":160},"groupIndex":1},{"__type__":"cc.Node","_name":"Splash3","_parent":{"__id__":1},"_components":[{"__type__":"cc.Sprite","node":{"__id__":9},"_spriteFrame":{"__uuid__":"a2MjXRFdtLlYQ5ouAFv/+R"},"_sizeMode":0},{"__type__":"cc.Widget","node":{"__id__":9},"_alignFlags":17,"_right":567,"_top":145,"_bottom":-50,"_horizontalCenter":45,"_originalWidth":100,"_originalHeight":150},{"__type__":"cc.RigidBody","node":{"__id__":9},"_type":0},{"__type__":"cc.BoxCollider","node":{"__id__":9},"_size":{"__type__":"cc.Size","width":35,"height":130}},{"__type__":"cc.PhysicsBoxCollider","node":{"__id__":9},"_size":{"__type__":"cc.Size","width":35,"height":130}}],"_prefab":{"__type__":"cc.PrefabInfo","root":{"__id__":1},"asset":{"__uuid__":"73M62JjrhDPrsa2yE8QD8X"},"fileId":"fcfbKVxqpIc7rEWoPxLJXd"},"_color":{"__type__":"cc.Color","r":107,"g":134,"b":197},"_contentSize":{"__type__":"cc.Size","width":35,"height":130},"_rotationX":50,"_rotationY":50,"_position":{"__type__":"cc.Vec2","x":45,"y":105},"groupIndex":1},{"__type__":"cc.Node","_name":"Splash4","_parent":{"__id__":1},"_components":[{"__type__":"cc.Sprite","node":{"__id__":10},"_spriteFrame":{"__uuid__":"a2MjXRFdtLlYQ5ouAFv/+R"},"_sizeMode":0},{"__type__":"cc.Widget","node":{"__id__":10},"_alignFlags":17,"_right":567,"_top":150,"_bottom":-50,"_horizontalCenter":-50,"_originalWidth":100,"_originalHeight":150},{"__type__":"cc.RigidBody","node":{"__id__":10},"_type":0},{"__type__":"cc.BoxCollider","node":{"__id__":10},"_size":{"__type__":"cc.Size","width":35,"height":120}},{"__type__":"cc.PhysicsBoxCollider","node":{"__id__":10},"_size":{"__type__":"cc.Size","width":35,"height":120}}],"_prefab":{"__type__":"cc.PrefabInfo","root":{"__id__":1},"asset":{"__uuid__":"73M62JjrhDPrsa2yE8QD8X"},"fileId":"59HV7wgB5Jo6PSXJmkqCk3"},"_color":{"__type__":"cc.Color","r":107,"g":134,"b":197},"_contentSize":{"__type__":"cc.Size","width":35,"height":120},"_rotationX":-50,"_rotationY":-50,"_position":{"__type__":"cc.Vec2","x":-50,"y":105},"groupIndex":1},{"__type__":"cc.Node","_name":"Splash5","_parent":{"__id__":1},"_components":[{"__type__":"cc.Sprite","node":{"__id__":11},"_spriteFrame":{"__uuid__":"f2fWwOD3dHvKFd+0k5HGNr"},"_sizeMode":0},{"__type__":"cc.Widget","node":{"__id__":11},"_alignFlags":12,"_right":567,"_top":110,"_horizontalCenter":-90,"_originalWidth":100,"_originalHeight":150},{"__type__":"cc.RigidBody","node":{"__id__":11},"_type":0},{"__type__":"cc.PolygonCollider","node":{"__id__":11},"points":[{"__type__":"cc.Vec2","x":-149.8,"y":-150.2},{"__type__":"cc.Vec2","x":150.4,"y":-150.2},{"__type__":"cc.Vec2","x":1.2,"y":150.6}]},{"__type__":"cc.PhysicsPolygonCollider","node":{"__id__":11},"points":[{"__type__":"cc.Vec2","x":-149,"y":-147},{"__type__":"cc.Vec2","x":152.1,"y":-149},{"__type__":"cc.Vec2","x":0.1,"y":149}]}],"_prefab":{"__type__":"cc.PrefabInfo","root":{"__id__":1},"asset":{"__uuid__":"73M62JjrhDPrsa2yE8QD8X"},"fileId":"3ax8bd/MNFsYLFDBM1JSv8"},"_color":{"__type__":"cc.Color","r":107,"g":134,"b":197},"_contentSize":{"__type__":"cc.Size","width":300,"height":300},"_position":{"__type__":"cc.Vec2","x":-410.28,"y":-165},"groupIndex":1},{"__type__":"cc.Node","_name":"Splash6","_parent":{"__id__":1},"_components":[{"__type__":"cc.Sprite","node":{"__id__":12},"_spriteFrame":{"__uuid__":"f2fWwOD3dHvKFd+0k5HGNr"},"_sizeMode":0},{"__type__":"cc.Widget","node":{"__id__":12},"_alignFlags":36,"_top":110,"_horizontalCenter":-90,"_originalWidth":100,"_originalHeight":150},{"__type__":"cc.RigidBody","node":{"__id__":12},"_type":0},{"__type__":"cc.PolygonCollider","node":{"__id__":12},"points":[{"__type__":"cc.Vec2","x":-149.8,"y":-150.2},{"__type__":"cc.Vec2","x":150.4,"y":-150.2},{"__type__":"cc.Vec2","x":1.2,"y":150.6}]},{"__type__":"cc.PhysicsPolygonCollider","node":{"__id__":12},"points":[{"__type__":"cc.Vec2","x":-149,"y":-149.8},{"__type__":"cc.Vec2","x":149,"y":-149.8},{"__type__":"cc.Vec2","x":-0.9,"y":150.5}]}],"_prefab":{"__type__":"cc.PrefabInfo","root":{"__id__":1},"asset":{"__uuid__":"73M62JjrhDPrsa2yE8QD8X"},"fileId":"3aZYAtG8NIUZFrqmesEx3f"},"_color":{"__type__":"cc.Color","r":107,"g":134,"b":197},"_contentSize":{"__type__":"cc.Size","width":300,"height":300},"_position":{"__type__":"cc.Vec2","x":410.28,"y":-165},"groupIndex":1}],{"__type__":"cc.SpriteFrame","content":{"name":"lb_ysc_female_01_1_1","texture":"ccareaIMlGprtT2mU17p30","rect":[0,0,73,61],"offset":[0,0],"originalSize":[73,61]}},{"__type__":"cc.SpriteFrame","content":{"name":"default_sprite_splash","texture":"02delMVqdBD70a/HSD99FK","rect":[0,0,2,2],"offset":[0,0],"originalSize":[2,2]}},{"__type__":"cc.SpriteFrame","content":{"name":"lb_ysc_Editor_Icon_rectangle2","texture":"39GMpLspRFqbTjd2kKX6QW","rect":[2,2,143,124],"offset":[0,0],"originalSize":[147,128]}}]